{
  "apiVersion": "1.0",
  "swaggerVersion": "1.2",
  "basePath": "http://localhost:3000",
  "resourcePath": "invoices",
  "apis": [
    {
      "path": "/api/v1/invoices/find.json",
      "operations": [
        {
          "summary": "Fetches single invoice item",
          "notes": "This returns a single invoice item record by attributes",
          "parameters": [
            {
              "paramType": "query",
              "name": "id",
              "type": "integer",
              "description": "id",
              "required": false
            },
            {
              "paramType": "query",
              "name": "customer_id",
              "type": "integer",
              "description": "customer_id",
              "required": false
            },
            {
              "paramType": "query",
              "name": "merchant_id",
              "type": "integer",
              "description": "merchant_id",
              "required": false
            },
            {
              "paramType": "query",
              "name": "created_at",
              "type": "datetime",
              "description": "created_at",
              "required": false
            },
            {
              "paramType": "query",
              "name": "find",
              "type": "datetime",
              "description": "updated_at",
              "required": false
            },
            {
              "paramType": "query",
              "name": "find",
              "type": "datetime",
              "description": "updated_at",
              "required": false
            }
          ],
          "responseMessages": [
            {
              "code": 404,
              "responseModel": null,
              "message": "Not Found"
            },
            {
              "code": 406,
              "responseModel": null,
              "message": "Not Acceptable"
            }
          ],
          "nickname": "Api::V1::Invoices#show",
          "method": "get"
        }
      ]
    },
    {
      "path": "/api/v1/invoices/find_all.json",
      "operations": [
        {
          "summary": "Fetches all invoices",
          "notes": "This lists all invoices, sortable by record attributes",
          "parameters": [
            {
              "paramType": "query",
              "name": "customer_id",
              "type": "integer",
              "description": "customer_id",
              "required": false
            },
            {
              "paramType": "query",
              "name": "merchant_id",
              "type": "integer",
              "description": "merchant_id",
              "required": false
            },
            {
              "paramType": "query",
              "name": "id",
              "type": "integer",
              "description": "id",
              "required": false
            },
            {
              "paramType": "query",
              "name": "created_at",
              "type": "string",
              "description": "created_at",
              "required": false
            },
            {
              "paramType": "query",
              "name": "updated_at",
              "type": "string",
              "description": "updated_at",
              "required": false
            }
          ],
          "responseMessages": [
            {
              "code": 404,
              "responseModel": null,
              "message": "Not Found"
            },
            {
              "code": 406,
              "responseModel": null,
              "message": "Not Acceptable"
            }
          ],
          "nickname": "Api::V1::Invoices#index",
          "method": "get"
        }
      ]
    }
  ],
  "authorizations": null
}